ovld/__init__.py
ovld/abc.py
ovld/codegen.py
ovld/core.py
ovld/dependent.py
ovld/medley.py
ovld/mro.py
ovld/py.typed
ovld/recode.py
ovld/signatures.py
ovld/typemap.py
ovld/types.py
ovld/utils.py
ovld/version.py
ovld-0.5.13.dist-info/METADATA
ovld-0.5.13.dist-info/WHEEL
ovld-0.5.13.dist-info/licenses/LICENSE
ovld-0.5.13.dist-info/RECORD
