Metadata-Version: 2.4
Name: ovld
Version: 0.5.13
Summary: Overloading Python functions
Project-URL: Homepage, https://ovld.readthedocs.io/en/latest/
Project-URL: Documentation, https://ovld.readthedocs.io/en/latest/
Project-URL: Repository, https://github.com/breuleux/ovld
Author-email: Olivier Breuleux <breuleux@gmail.com>
License-Expression: MIT
License-File: LICENSE
Requires-Python: >=3.9
